CAMIViz-0.1.1.dist-info/DESCRIPTION.rst
CAMIViz-0.1.1.dist-info/METADATA
CAMIViz-0.1.1.dist-info/RECORD
CAMIViz-0.1.1.dist-info/WHEEL
CAMIViz-0.1.1.dist-info/entry_points.txt
CAMIViz-0.1.1.dist-info/metadata.json
CAMIViz-0.1.1.dist-info/top_level.txt
src/ProfilesLayout.py
src/__init__.py
src/load_data.py
src/profile_to_plot.py
