Metadata-Version: 2.0
Name: CAMIViz
Version: 0.1.1
Summary: A collection of tools to visualize CAMI profiling outputs
Home-page: https://github.com/dkoslicki/CAMIProfilingVisualization
Author: David Koslicki
Author-email: dmk333@psu.edu
License: MIT
Keywords: profile_to_plot src python package
Platform: UNKNOWN
Classifier: Programming Language :: Python :: 3
Classifier: License :: OSI Approved :: MIT License
Classifier: Operating System :: OS Independent
Requires-Dist: biom-format
Requires-Dist: ete3
Requires-Dist: matplotlib
Requires-Dist: numpy
Requires-Dist: pandas
Requires-Dist: seaborn
